nbsync/__init__.py
nbsync/cell.py
nbsync/logger.py
nbsync/markdown.py
nbsync/notebook.py
nbsync/py.typed
nbsync/sync.py
nbsync-0.4.3.dist-info/WHEEL
nbsync-0.4.3.dist-info/METADATA
nbsync-0.4.3.dist-info/RECORD
