Metadata-Version: 2.3
Name: nbsync
Version: 0.4.3
Summary: A core library to synchronize Jupyter notebooks and Markdown documents, enabling seamless integration and dynamic content execution
Keywords: jupyter,notebook,documentation,markdown,python,visualization,dynamic-execution,real-time-sync
Author: daizutabi
Author-email: daizutabi <daizutabi@gmail.com>
License: MIT License
Classifier: Development Status :: 4 - Beta
Classifier: Programming Language :: Python
Classifier: Programming Language :: Python :: 3.10
Classifier: Programming Language :: Python :: 3.11
Classifier: Programming Language :: Python :: 3.12
Classifier: Programming Language :: Python :: 3.13
Classifier: Programming Language :: Python :: 3.14
Classifier: Topic :: Documentation
Classifier: Topic :: Software Development :: Documentation
Classifier: Topic :: Text Processing :: Markup :: Markdown
Requires-Dist: nbstore>=0.5.2
Requires-Python: >=3.10
Project-URL: Changelog, https://github.com/daizutabi/nbsync/releases
Project-URL: Documentation, https://daizutabi.github.io/nbsync/
Project-URL: Homepage, https://daizutabi.github.io/nbsync/
Project-URL: Issues, https://github.com/daizutabi/nbsync/issues
Project-URL: Source, https://github.com/daizutabi/nbsync
